README.md
setup.cfg
setup.py
sgl/__init__.py
sgl/api.py
sgl/condition.py
sgl/dbc.py
sgl/principal.py
sgl/rule.py
sgl.egg-info/PKG-INFO
sgl.egg-info/SOURCES.txt
sgl.egg-info/dependency_links.txt
sgl.egg-info/entry_points.txt
sgl.egg-info/top_level.txt