Metadata-Version: 2.1
Name: sgl
Version: 0.9.17
Summary: Simple Grant Language
Home-page: https://github.com/evernym/sgl
Author: Daniel Hardman
Author-email: daniel.hardman@gmail.com
License: Apache 2.0
Download-URL: https://github.com/evernym/sgl/archive/v0.9.17.tar.gz
Keywords: sgl json dsl xacml authorization authz verifiable credentials did
Platform: UNKNOWN
Classifier: License :: OSI Approved :: Apache Software License
Classifier: Programming Language :: Python :: 3
Classifier: Programming Language :: Python :: 3.5
Classifier: Programming Language :: Python :: 3.6
Classifier: Programming Language :: Python :: 3.7
Classifier: Development Status :: 4 - Beta
